pulp_rpm_webhook/__init__.py
pulp_rpm_webhook/app/__init__.py
pulp_rpm_webhook/app/signals.py
pulp_rpm_webhook/app/webhook.py
pulp_rpm_webhook-0.1.0.dist-info/licenses/LICENSE
pulp_rpm_webhook-0.1.0.dist-info/METADATA
pulp_rpm_webhook-0.1.0.dist-info/WHEEL
pulp_rpm_webhook-0.1.0.dist-info/entry_points.txt
pulp_rpm_webhook-0.1.0.dist-info/top_level.txt
pulp_rpm_webhook-0.1.0.dist-info/RECORD
