Metadata-Version: 2.4
Name: pulp_rpm_webhook
Version: 0.1.0
Summary: Pulp plugin to trigger webhooks on RPM package uploads
Author-email: Jaroslav Stepanek <jaroslav@stepanek.eu>
Project-URL: Repository, https://github.com/cz-guardian/pulp_rpm_webhook
Project-URL: Bug Tracker, https://github.com/cz-guardian/pulp_rpm_webhook/issues
Classifier: License :: OSI Approved :: GNU General Public License v2 or later (GPLv2+)
Classifier: Operating System :: POSIX :: Linux
Classifier: Development Status :: 5 - Production/Stable
Classifier: Framework :: Django
Classifier: Programming Language :: Python
Classifier: Programming Language :: Python :: 3
Classifier: Programming Language :: Python :: 3.9
Classifier: Programming Language :: Python :: 3.10
Classifier: Programming Language :: Python :: 3.11
Classifier: Programming Language :: Python :: 3.12
Classifier: Programming Language :: Python :: 3.13
Requires-Python: >=3.9
License-File: LICENSE
Requires-Dist: pulpcore>=3.0.0
Requires-Dist: pulp_rpm>=3.0.0
Requires-Dist: requests>=2.25.0
Dynamic: license-file
